prosafe_exporter/__init__.py
prosafe_exporter/__main__.py
prosafe_exporter/_version.py
prosafe_exporter/prosafe_exporter_base.py
prosafe_exporter-0.4.7.dist-info/METADATA
prosafe_exporter-0.4.7.dist-info/WHEEL
prosafe_exporter-0.4.7.dist-info/entry_points.txt
prosafe_exporter-0.4.7.dist-info/top_level.txt
prosafe_exporter-0.4.7.dist-info/RECORD
