Metadata-Version: 2.1
Name: prosafe-exporter
Version: 0.4.7
Summary: Prometheus metrics exporter for NETGEAR switches of the Smart Managed Plus series.
Home-page: https://github.com/tillsteinbach/prosafe_exporter_python
Author: Till Steinbach
License: MIT
Keywords: prometheus,netgear,metrics-exporter,prosafe,prosafe-exporter
Platform: UNKNOWN
Classifier: Development Status :: 4 - Beta
Classifier: License :: OSI Approved :: MIT License
Classifier: Intended Audience :: System Administrators
Classifier: Programming Language :: Python :: 3.6
Classifier: Topic :: System :: Networking :: Monitoring 
Requires-Python: >=3.6
Requires-Dist: Flask (>=1.1.2)
Requires-Dist: lxml (>=4.6.3)
Requires-Dist: requests (>=2.23.0)
Requires-Dist: PyYAML (>=4.6.3)
